fparse
