Metadata-Version: 2.1
Name: fparse
Version: 1.20.1
Summary: parse() is the opposite of format()
Home-page: https://github.com/catalystneuro/fparse
Author: Richard Jones & Ben Dichter
Author-email: ben.dichter@catalystneuro.com
Classifier: Environment :: Web Environment
Classifier: Intended Audience :: Developers
Classifier: Programming Language :: Python :: 3.7
Classifier: Programming Language :: Python :: 3.8
Classifier: Programming Language :: Python :: 3.9
Classifier: Programming Language :: Python :: 3.10
Classifier: Programming Language :: Python :: 3.11
Classifier: Topic :: Software Development :: Code Generators
Classifier: Topic :: Software Development :: Libraries :: Python Modules
Classifier: License :: OSI Approved :: BSD License
License-File: LICENSE
